_solpos.abi3.so
solpos.py
solpos-0.1.2.dist-info/LICENSE
solpos-0.1.2.dist-info/METADATA
solpos-0.1.2.dist-info/WHEEL
solpos-0.1.2.dist-info/top_level.txt
solpos-0.1.2.dist-info/RECORD
