Metadata-Version: 2.1
Name: solpos
Version: 0.1.2
Summary: a python wrapper around NREL SOLPOS 2.0
Home-page: https://github.com/jkittner/solpos
Author: Jonas Kittner
Author-email: jkittner@users.noreply.github.com
License: MIT
Classifier: License :: OSI Approved :: MIT License
Classifier: Programming Language :: Python :: 3
Classifier: Programming Language :: Python :: 3 :: Only
Classifier: Programming Language :: Python :: Implementation :: CPython
Requires-Python: >=3.7
License-File: LICENSE
